surveyweights/__init__.py
surveyweights/weighting.py
surveyweights/census/__init__.py
surveyweights/census/uk_census.py
surveyweights/census/us_census.py
surveyweights-0.6.dist-info/LICENSE.txt
surveyweights-0.6.dist-info/METADATA
surveyweights-0.6.dist-info/WHEEL
surveyweights-0.6.dist-info/top_level.txt
surveyweights-0.6.dist-info/RECORD
