Metadata-Version: 2.1
Name: surveyweights
Version: 0.6
Summary: Apply Census weighting to survey data
Home-page: https://github.com/rethinkpriorities/surveyweights
Author: Peter Hurford
Author-email: peter@peterhurford.com
License: UNKNOWN
Platform: UNKNOWN
Classifier: Development Status :: 3 - Alpha
Classifier: Programming Language :: Python :: 3
Classifier: License :: OSI Approved :: MIT License
Classifier: Operating System :: OS Independent
